odoo/addons/web_excel_export_dynamic_expand/README.rst
odoo/addons/web_excel_export_dynamic_expand/__init__.py
odoo/addons/web_excel_export_dynamic_expand/__manifest__.py
odoo/addons/web_excel_export_dynamic_expand/controllers/__init__.py
odoo/addons/web_excel_export_dynamic_expand/controllers/excel_export.py
odoo/addons/web_excel_export_dynamic_expand/i18n/it.po
odoo/addons/web_excel_export_dynamic_expand/i18n/web_excel_export_dynamic_expand.pot
odoo/addons/web_excel_export_dynamic_expand/readme/CONTRIBUTORS.md
odoo/addons/web_excel_export_dynamic_expand/readme/DESCRIPTION.md
odoo/addons/web_excel_export_dynamic_expand/static/description/icon.png
odoo/addons/web_excel_export_dynamic_expand/static/description/index.html
odoo/addons/web_excel_export_dynamic_expand/static/src/js/data_export.esm.js
odoo_addon_web_excel_export_dynamic_expand-18.0.1.0.0.3.dist-info/METADATA
odoo_addon_web_excel_export_dynamic_expand-18.0.1.0.0.3.dist-info/WHEEL
odoo_addon_web_excel_export_dynamic_expand-18.0.1.0.0.3.dist-info/top_level.txt
odoo_addon_web_excel_export_dynamic_expand-18.0.1.0.0.3.dist-info/RECORD
