Metadata-Version: 2.1
Name: odoo-addon-web_excel_export_dynamic_expand
Version: 18.0.1.0.0.3
Requires-Python: >=3.10
Requires-Dist: odoo==18.0.*
Summary: Export collapsed groups or the full tree, based on its view.
Home-page: https://github.com/OCA/web
License: AGPL-3
Author: ForgeFlow, Odoo Community Association (OCA)
Author-email: support@odoo-community.org
Classifier: Programming Language :: Python
Classifier: Framework :: Odoo
Classifier: Framework :: Odoo :: 18.0
Classifier: License :: OSI Approved :: GNU Affero General Public License v3
